{
  "project_info": {
    "project_number": "951815017189",
    "project_id": "geofence-remider",
    "storage_bucket": "geofence-remider.appspot.com"
  },
  "client": [
    {
      "client_info": {
        "mobilesdk_app_id": "1:951815017189:android:866cf7e755ebe3685a3a0c",
        "android_client_info": {
          "package_name": "com.udacity.project4"
        }
      },
      "oauth_client": [
        {
          "client_id": "951815017189-c9ckmvljp94o7bia5rhta33hag35hacl.apps.googleusercontent.com",
          "client_type": 1,
          "android_info": {
            "package_name": "com.udacity.project4",
            "certificate_hash": "d197b94228cfbd96a8115e9d41ea3e197b665ef1"
          }
        },
        {
          "client_id": "951815017189-7la8cam71clhq0qqa5o2m03na6uqmoe1.apps.googleusercontent.com",
          "client_type": 3
        }
      ],
      "api_key": [
        {
          "current_key": "AIzaSyAFhG8vzI8UFrANOqwYQuWRukSfJKNaw6Q"
        }
      ],
      "services": {
        "appinvite_service": {
          "other_platform_oauth_client": [
            {
              "client_id": "951815017189-7la8cam71clhq0qqa5o2m03na6uqmoe1.apps.googleusercontent.com",
              "client_type": 3
            }
          ]
        }
      }
    }
  ],
  "configuration_version": "1"
}